README.md
setup.py
markov_cli/__init__.py
markov_cli.egg-info/PKG-INFO
markov_cli.egg-info/SOURCES.txt
markov_cli.egg-info/dependency_links.txt
markov_cli.egg-info/requires.txt
markov_cli.egg-info/top_level.txt
utils/markov-cli